json_log_formatter/__init__.py
python3_json_log_formatter/__init__.py
python3_json_log_formatter/test.py
python3_json_log_formatter-1.6.1.dist-info/METADATA
python3_json_log_formatter-1.6.1.dist-info/RECORD
python3_json_log_formatter-1.6.1.dist-info/WHEEL
python3_json_log_formatter-1.6.1.dist-info/top_level.txt
