Metadata-Version: 2.1
Name: python3-json-log-formatter
Version: 1.6.1
Summary: Json Log Formatter
